freetube_import/__init__.py
freetube_import/freetube_import.py
freetube_import/youtube_search.py
freetube_import-0.38.0.dist-info/licenses/LICENSE
freetube_import-0.38.0.dist-info/METADATA
freetube_import-0.38.0.dist-info/WHEEL
freetube_import-0.38.0.dist-info/entry_points.txt
freetube_import-0.38.0.dist-info/top_level.txt
freetube_import-0.38.0.dist-info/RECORD
