Metadata-Version: 2.4
Name: freetube-import
Version: 0.38.0
Summary: Converts text and youtube .csv files into FreeTube playlists
Author: NoSpiner
License-Expression: MIT
Project-URL: Homepage, https://github.com/NoSpiner/Freetube-import
Project-URL: Issues, https://github.com/NoSpiner/Freetube-import/issues
Keywords: freetube,youtube,tube,playlist,import,cli,console,video,videos
Classifier: Programming Language :: Python :: 3
Classifier: Operating System :: OS Independent
Requires-Python: >=3.8
License-File: LICENSE
Requires-Dist: tqdm
Requires-Dist: requests
Dynamic: license-file
